pretty_help/__init__.py
pretty_help/abc_menu.py
pretty_help/app_menu.py
pretty_help/emoji_menu.py
pretty_help/pretty_help.py
discord_pretty_help-2.0.6.dist-info/entry_points.txt
discord_pretty_help-2.0.6.dist-info/LICENSE
discord_pretty_help-2.0.6.dist-info/METADATA
discord_pretty_help-2.0.6.dist-info/WHEEL
discord_pretty_help-2.0.6.dist-info/RECORD
