Metadata-Version: 2.1
Name: discord-pretty-help
Version: 2.0.6
Summary: And nicer looking interactive help menu for discord.py
Home-page: https://github.com/casuallycalm/discord-pretty-help
License: MIT
Keywords: discord,discord.py,discord bot
Author: CasuallyCalm
Author-email: 29642143+casuallycalm@users.noreply.github.com
Requires-Python: >=3.8,<4.0
Classifier: License :: OSI Approved :: MIT License
Classifier: Programming Language :: Python :: 3
Classifier: Programming Language :: Python :: 3.8
Classifier: Programming Language :: Python :: 3.9
Classifier: Programming Language :: Python :: 3.10
Classifier: Programming Language :: Python :: 3.11
Project-URL: Repository, https://github.com/casuallycalm/discord-pretty-help
